page_eyes/__init__.py
page_eyes/agent.py
page_eyes/config.py
page_eyes/deps.py
page_eyes/device.py
page_eyes/prompt.py
page_eyes/prompt_back.py
page_eyes/report_template.html
page_eyes/tools.py
page_eyes/util/__init__.py
page_eyes/util/adb_tool.py
page_eyes/util/platform.py
page_eyes/util/storage.py
page_eyes/util/bin/yadb
page_eyes/util/js_tool/__init__.py
page_eyes/util/js_tool/script.js
page_eyes-1.1.4.dist-info/METADATA
page_eyes-1.1.4.dist-info/WHEEL
page_eyes-1.1.4.dist-info/licenses/LICENSE
page_eyes-1.1.4.dist-info/RECORD
