Metadata-Version: 2.4
Name: page-eyes
Version: 1.1.4
Summary: PageEyes Agent 是一个轻量级 UI Agent，通过自然语言指令驱动，无需编写脚本既可实现Web、Android平台的UI自动化任务。
Project-URL: Homepage, https://github.com/tencentmusic/page-eyes-agent
Project-URL: Documentation, https://github.com/tencentmusic/page-eyes-agent
Project-URL: Repository, https://github.com/tencentmusic/page-eyes-agent
Project-URL: Changelog, https://github.com/tencentmusic/page-eyes-agent/blob/main/CHANGELOG.md
Author-email: aidenmo <aidenmo@tencent.com>
Maintainer-email: bepoxu <bepoxu@tencent.com>, leenjiang <leenjiang@tencent.com>, xinlanshi <xinlanshi@tencent.com>, yicanguo <yicanguo@tencent.com>, lancefayang <lancefayang@tencent.com>, aidenmo <aidenmo@tencent.com>
License-File: LICENSE
Classifier: Development Status :: 4 - Beta
Classifier: Intended Audience :: Developers
Classifier: License :: OSI Approved :: MIT License
Classifier: Programming Language :: Python :: 3.10
Classifier: Programming Language :: Python :: 3.11
Classifier: Programming Language :: Python :: 3.12
Classifier: Topic :: Software Development :: Build Tools
Requires-Python: >=3.12
Requires-Dist: adbutils>=2.8.10
Requires-Dist: cos-python-sdk-v5>=1.9.38
Requires-Dist: esprima2>=5.0.0
Requires-Dist: loguru>=0.7.3
Requires-Dist: minio>=7.2.16
Requires-Dist: playwright>=1.52.0
Requires-Dist: pydantic-ai==0.3.4
